relationaldb/__init__.py
relationaldb/bases.py
relationaldb/conception.py
relationaldb/consts.py
relationaldb/entities.py
relationaldb/exceptions.py
relationaldb/mongodb.py
relationaldb/mongodb_builder.py
relationaldb/simpledb.py
relationaldb/sqldb.py
relationaldb/utils.py
relationaldb/data/mongodb_template.jinja2
relationaldb-0.1.1.dist-info/LICENSE
relationaldb-0.1.1.dist-info/METADATA
relationaldb-0.1.1.dist-info/WHEEL
relationaldb-0.1.1.dist-info/top_level.txt
relationaldb-0.1.1.dist-info/RECORD
